pr_review/.gitignore
pr_review/__init__.py
pr_review/check_coding_standards.py
pr_review/config.py
pr_review/definitions.py
pr_review/output_schemas/CodingStandardsReview.py
pr_review/output_schemas/__init__.py
pr_review/settings/check_coding_standards.toml
pr_review/utils/__init__.py
pr_review/utils/read_text.py
pr_review-0.0.0.1.dist-info/METADATA
pr_review-0.0.0.1.dist-info/WHEEL
pr_review-0.0.0.1.dist-info/entry_points.txt
pr_review-0.0.0.1.dist-info/RECORD
