Metadata-Version: 2.1
Name: pr-review
Version: 0.0.0.1
Summary: A tool to check wolfSSL coding standards
Author: Shingo Morimoto
Author-email: shingo@wolfssl.com
Requires-Python: >=3.9,<4.0
Classifier: Programming Language :: Python :: 3
Classifier: Programming Language :: Python :: 3.9
Classifier: Programming Language :: Python :: 3.10
Classifier: Programming Language :: Python :: 3.11
Classifier: Programming Language :: Python :: 3.12
Requires-Dist: dynaconf (>=3.2.4,<4.0.0)
Requires-Dist: gitpython (>=3.1.42,<4.0.0)
Requires-Dist: langchain (>=0.1.10,<0.2.0)
Requires-Dist: langchain-community (>=0.0.25,<0.0.26)
Requires-Dist: langchain-openai (>=0.0.8,<0.0.9)
Requires-Dist: openai (>=1.13.3,<2.0.0)
Requires-Dist: pygithub (>=2.2.0,<3.0.0)
Requires-Dist: pytest (>=8.0.2,<9.0.0)
Requires-Dist: python-dotenv (>=1.0.1,<2.0.0)
